iofog/__init__.py
iofog/microservices/__init__.py
iofog/microservices/client.py
iofog/microservices/definitions.py
iofog/microservices/exception.py
iofog/microservices/httpclient.py
iofog/microservices/iomessage.py
iofog/microservices/listener.py
iofog/microservices/log.py
iofog/microservices/util.py
iofog/microservices/wsclient.py
iofog/rest/__init__.py
iofog/rest/controller/__init__.py
iofog/rest/controller/client.py
iofog/rest/controller/request.py
iofog-0.0.10.dist-info/METADATA
iofog-0.0.10.dist-info/WHEEL
iofog-0.0.10.dist-info/top_level.txt
iofog-0.0.10.dist-info/RECORD
