Metadata-Version: 2.1
Name: iofog
Version: 0.0.10
Summary: Python SDK for Eclipse ioFog development.
Home-page: https://github.com/eclipse-iofog/iofog-python-sdk
Author: Eclipse ioFog
Author-email: edgemaster@iofog.org
License: EPL-2.0
Project-URL: Source, https://github.com/eclipse-iofog/iofog-python-sdk.git
Project-URL: Eclipse ioFog, http://iofog.org
Project-URL: Documentation, https://github.com/eclipse-iofog/iofog-python-sdk/blob/master/README.md
Project-URL: Tracker, https://github.com/eclipse-iofog/iofog-python-sdk/issues
Keywords: ioFog IoT Eclipse fog computing edgeworx
Platform: UNKNOWN
Requires: ws4py
Requires: json
Requires: requests
